beewars/__init__.py
beewars/main.py
beewars/symbols.py
beewars-0.1.8.dist-info/LICENSE
beewars-0.1.8.dist-info/METADATA
beewars-0.1.8.dist-info/WHEEL
beewars-0.1.8.dist-info/entry_points.txt
beewars-0.1.8.dist-info/top_level.txt
beewars-0.1.8.dist-info/RECORD
