Metadata-Version: 2.1
Name: beewars
Version: 0.1.8
Summary: BeeWars (Game)
Home-page: https://github.com/poyynt/beewars/
Author: Parsa Torbati
Author-email: parsa@programmer.net
License: UNKNOWN
Platform: UNKNOWN
Classifier: Programming Language :: Python :: 3
Classifier: License :: OSI Approved :: GNU General Public License (GPL)
Classifier: Operating System :: OS Independent
Classifier: Development Status :: 5 - Production/Stable
Classifier: Natural Language :: English
Classifier: Topic :: Games/Entertainment
Requires-Python: >=3.2
Requires-Dist: pygame
Requires-Dist: numpy
